<?xml version="1.0" encoding="UTF-8"?>
<!DOCTYPE hibernate-mapping PUBLIC "-//Hibernate/Hibernate Mapping DTD 3.0//EN" "http://www.hibernate.org/dtd/hibernate-mapping-3.0.dtd">
<!-- Generated 4 juin 2016 18:10:50 by Hibernate Tools 4.3.1 -->
<hibernate-mapping>
  <class catalog="finance_fssm" name="modele.Anneebudgetaire" optimistic-lock="version" table="anneebudgetaire">
    <id name="annee" type="java.lang.Integer">
      <column name="annee"/>
      <generator class="identity"/>
    </id>
    <property name="montantRap" type="java.lang.Integer">
      <column name="montantRap" precision="8" scale="0"/>
    </property>
    <property name="reliquatRap" type="java.lang.Integer">
      <column name="reliquatRap" precision="8" scale="0"/>
    </property>
  </class>
</hibernate-mapping>
